[
  {
    "id": "1825380563",
    "score": 1.0,
    "spell": {
      "id": 111,
      "key": "GEAS_ES",
      "version": "1",
      "main": true,
      "facet_disabled": false,
      "default_sorting": "DEFAULT",
      "response_type": "ARRAY"
    },
    "status": {
      "status": "active",
      "allow_edit": true,
      "display": "active",
      "translated_display": "Active",
      "flags": {
        "new": false,
        "hot": false
      },
      "allow_deactivate": true
    },
    "category_id": "93",
    "ad_id": "1825380563",
    "favorites": {
      "count": 0,
      "count_label_next": "1"
    },
    "user_tag": "olx disapproved",
    "user_name": "Harshit Dhingra ",
    "has_phone_param": false,
    "description": "Selling below PS4 games at throwaway prices. Can also exchange with equivalent value games. Each game has individual cost so please read the full ad carefully before quoting your offer.\n\nGost of Tsushima: \u20b91800\nLast of us Remastered: \u20b91000\nWwe 2k20: \u20b91500\nWWE 2k22: \u20b91500\nCOD Blackops4: \u20b91500\nFiFa 17: \u20b9300\n\nPrice slightly negotiable and if u buy complete bundle can give u FIFA 17 for free",
    "created_at": "2025-11-03T21:11:09+05:30",
    "videos": [],
    "title": "Pre-Owned PS4 games in excellent and in working condition.",
    "buyer_id": "0",
    "elite_seller": false,
    "user_type": "Regular",
    "price": {
      "value": {
        "raw": 7500.0,
        "currency": {
          "iso_4217": "INR",
          "pre": "\u20b9"
        },
        "display": "\u20b9 7,500"
      },
      "key_name": "Price",
      "key": "price"
    },
    "is_business": false,
    "images": [
      {
        "id": "1951294388",
        "external_id": "2o8s5l1h5jlt3-IN",
        "width": 810,
        "height": 1080,
        "url": "https://apollo.olx.in:443/v1/files/2o8s5l1h5jlt3-IN/image",
        "full": {
          "width": 1080,
          "height": 1440,
          "url": "https://apollo.olx.in:443/v1/files/2o8s5l1h5jlt3-IN/image;s=1080x1440"
        },
        "big": {
          "width": 505,
          "height": 673,
          "url": "https://apollo.olx.in:443/v1/files/2o8s5l1h5jlt3-IN/image;s=505x673"
        },
        "medium": {
          "width": 120,
          "height": 160,
          "url": "https://apollo.olx.in:443/v1/files/2o8s5l1h5jlt3-IN/image;s=120x160"
        },
        "small": {
          "width": 120,
          "height": 160,
          "url": "https://apollo.olx.in:443/v1/files/2o8s5l1h5jlt3-IN/image;s=120x160"
        }
      },
      {
        "id": "1951294389",
        "external_id": "zxr6kw09zl0h3-IN",
        "width": 810,
        "height": 1080,
        "url": "https://apollo.olx.in:443/v1/files/zxr6kw09zl0h3-IN/image",
        "full": {
          "width": 1080,
          "height": 1440,
          "url": "https://apollo.olx.in:443/v1/files/zxr6kw09zl0h3-IN/image;s=1080x1440"
        },
        "big": {
          "width": 505,
          "height": 673,
          "url": "https://apollo.olx.in:443/v1/files/zxr6kw09zl0h3-IN/image;s=505x673"
        },
        "medium": {
          "width": 120,
          "height": 160,
          "url": "https://apollo.olx.in:443/v1/files/zxr6kw09zl0h3-IN/image;s=120x160"
        },
        "small": {
          "width": 120,
          "height": 160,
          "url": "https://apollo.olx.in:443/v1/files/zxr6kw09zl0h3-IN/image;s=120x160"
        }
      },
      {
        "id": "1951294390",
        "external_id": "7vw926wk6wnl3-IN",
        "width": 810,
        "height": 1080,
        "url": "https://apollo.olx.in:443/v1/files/7vw926wk6wnl3-IN/image",
        "full": {
          "width": 1080,
          "height": 1440,
          "url": "https://apollo.olx.in:443/v1/files/7vw926wk6wnl3-IN/image;s=1080x1440"
        },
        "big": {
          "width": 505,
          "height": 673,
          "url": "https://apollo.olx.in:443/v1/files/7vw926wk6wnl3-IN/image;s=505x673"
        },
        "medium": {
          "width": 120,
          "height": 160,
          "url": "https://apollo.olx.in:443/v1/files/7vw926wk6wnl3-IN/image;s=120x160"
        },
        "small": {
          "width": 120,
          "height": 160,
          "url": "https://apollo.olx.in:443/v1/files/7vw926wk6wnl3-IN/image;s=120x160"
        }
      }
    ],
    "certified_car": false,
    "is_kyc_verified_user": false,
    "locations_resolved": {
      "COUNTRY_id": "1000001",
      "COUNTRY_name": "India",
      "ADMIN_LEVEL_1_id": "2001152",
      "ADMIN_LEVEL_1_name": "Delhi",
      "ADMIN_LEVEL_3_id": "4058659",
      "ADMIN_LEVEL_3_name": "Delhi",
      "SUBLOCALITY_LEVEL_1_id": "5459480",
      "SUBLOCALITY_LEVEL_1_name": "Rohini"
    },
    "dealer_showroom_enabled": false,
    "artificial_boost": false,
    "display_date": "2025-11-03T13:31:18+0000",
    "isSpinViewAvailable": false,
    "user_id": "85073603",
    "created_at_first": "2025-11-03T19:00:18+05:30",
    "locations": [
      {
        "lat": 28.749,
        "lon": 77.056,
        "region_id": "2001152",
        "district_id": "5459480",
        "city_id": "4058659"
      }
    ],
    "parameters": []
  }
]