[
  {
    "id": "1825091532",
    "score": 0.9047619047619048,
    "spell": {
      "id": 111,
      "key": "GEAS_ES",
      "version": "1",
      "main": true,
      "facet_disabled": false,
      "default_sorting": "DEFAULT",
      "response_type": "ARRAY"
    },
    "status": {
      "status": "active",
      "allow_edit": true,
      "display": "active",
      "translated_display": "Active",
      "flags": {
        "new": false,
        "hot": false
      },
      "allow_deactivate": true
    },
    "category_id": "93",
    "ad_id": "1825091532",
    "favorites": {
      "count": 0,
      "count_label_next": "1"
    },
    "user_tag": "olx disapproved",
    "user_name": "JeK",
    "has_phone_param": false,
    "description": "Authentic PS5 and PS4 original sealed games available at unbeatable wholesale prices! We offer genuine, brand-new, factory-sealed discs direct from authorized distributors.Why Choose Us:100% authentic and original gamesSealed packaging guaranteeWholesale rates - much cheaper than market priceDirect pickup available across Delhi NCRFast delivery serviceHow It Works:Browse and select your favorite PS5 or PS4 gamePlace your order with game preference at least 2.5 days in advanceWe arrange and prepare your stock quicklyPick up directly from our location in Delhi NCRDelivery: Personal pickup only from our Delhi NCR location. We ensure fast processing to get your games to you as soon as possible.Available For: PS5 Games  PS4 Games  Original Sealed CDs  Wholesale Bulk OrdersContact us today for stock availability and exclusive wholesale rates!",
    "created_at": "2025-10-31T20:06:02+05:30",
    "videos": [],
    "title": "Original Sealed PS5 & PS4 Games Wholesale Prices Delhi NCR Pickup Only",
    "buyer_id": "0",
    "elite_seller": false,
    "user_type": "Regular",
    "price": {
      "value": {
        "raw": 4893.0,
        "currency": {
          "iso_4217": "INR",
          "pre": "\u20b9"
        },
        "display": "\u20b9 4,893"
      },
      "key_name": "Price",
      "key": "price"
    },
    "is_business": false,
    "images": [
      {
        "id": "1949819165",
        "external_id": "7m1fkqx1vtrq-IN",
        "width": 845,
        "height": 1080,
        "url": "https://apollo.olx.in:443/v1/files/7m1fkqx1vtrq-IN/image",
        "full": {
          "width": 1080,
          "height": 1380,
          "url": "https://apollo.olx.in:443/v1/files/7m1fkqx1vtrq-IN/image;s=1080x1380"
        },
        "big": {
          "width": 505,
          "height": 645,
          "url": "https://apollo.olx.in:443/v1/files/7m1fkqx1vtrq-IN/image;s=505x645"
        },
        "medium": {
          "width": 120,
          "height": 153,
          "url": "https://apollo.olx.in:443/v1/files/7m1fkqx1vtrq-IN/image;s=120x153"
        },
        "small": {
          "width": 120,
          "height": 153,
          "url": "https://apollo.olx.in:443/v1/files/7m1fkqx1vtrq-IN/image;s=120x153"
        }
      },
      {
        "id": "1949819166",
        "external_id": "676v4v8t5t3f3-IN",
        "width": 827,
        "height": 1080,
        "url": "https://apollo.olx.in:443/v1/files/676v4v8t5t3f3-IN/image",
        "full": {
          "width": 1080,
          "height": 1410,
          "url": "https://apollo.olx.in:443/v1/files/676v4v8t5t3f3-IN/image;s=1080x1410"
        },
        "big": {
          "width": 505,
          "height": 659,
          "url": "https://apollo.olx.in:443/v1/files/676v4v8t5t3f3-IN/image;s=505x659"
        },
        "medium": {
          "width": 120,
          "height": 156,
          "url": "https://apollo.olx.in:443/v1/files/676v4v8t5t3f3-IN/image;s=120x156"
        },
        "small": {
          "width": 120,
          "height": 156,
          "url": "https://apollo.olx.in:443/v1/files/676v4v8t5t3f3-IN/image;s=120x156"
        }
      },
      {
        "id": "1949819167",
        "external_id": "aam4iqeuauj21-IN",
        "width": 835,
        "height": 1080,
        "url": "https://apollo.olx.in:443/v1/files/aam4iqeuauj21-IN/image",
        "full": {
          "width": 1080,
          "height": 1396,
          "url": "https://apollo.olx.in:443/v1/files/aam4iqeuauj21-IN/image;s=1080x1396"
        },
        "big": {
          "width": 505,
          "height": 653,
          "url": "https://apollo.olx.in:443/v1/files/aam4iqeuauj21-IN/image;s=505x653"
        },
        "medium": {
          "width": 120,
          "height": 155,
          "url": "https://apollo.olx.in:443/v1/files/aam4iqeuauj21-IN/image;s=120x155"
        },
        "small": {
          "width": 120,
          "height": 155,
          "url": "https://apollo.olx.in:443/v1/files/aam4iqeuauj21-IN/image;s=120x155"
        }
      },
      {
        "id": "1949819168",
        "external_id": "azicylofn0xg-IN",
        "width": 712,
        "height": 1080,
        "url": "https://apollo.olx.in:443/v1/files/azicylofn0xg-IN/image",
        "full": {
          "width": 1080,
          "height": 1638,
          "url": "https://apollo.olx.in:443/v1/files/azicylofn0xg-IN/image;s=1080x1638"
        },
        "big": {
          "width": 505,
          "height": 766,
          "url": "https://apollo.olx.in:443/v1/files/azicylofn0xg-IN/image;s=505x766"
        },
        "medium": {
          "width": 120,
          "height": 182,
          "url": "https://apollo.olx.in:443/v1/files/azicylofn0xg-IN/image;s=120x182"
        },
        "small": {
          "width": 120,
          "height": 182,
          "url": "https://apollo.olx.in:443/v1/files/azicylofn0xg-IN/image;s=120x182"
        }
      },
      {
        "id": "1949819169",
        "external_id": "759w826kzq8w1-IN",
        "width": 833,
        "height": 1080,
        "url": "https://apollo.olx.in:443/v1/files/759w826kzq8w1-IN/image",
        "full": {
          "width": 1080,
          "height": 1400,
          "url": "https://apollo.olx.in:443/v1/files/759w826kzq8w1-IN/image;s=1080x1400"
        },
        "big": {
          "width": 505,
          "height": 654,
          "url": "https://apollo.olx.in:443/v1/files/759w826kzq8w1-IN/image;s=505x654"
        },
        "medium": {
          "width": 120,
          "height": 155,
          "url": "https://apollo.olx.in:443/v1/files/759w826kzq8w1-IN/image;s=120x155"
        },
        "small": {
          "width": 120,
          "height": 155,
          "url": "https://apollo.olx.in:443/v1/files/759w826kzq8w1-IN/image;s=120x155"
        }
      },
      {
        "id": "1949819170",
        "external_id": "s3zc0bw7wtek-IN",
        "width": 698,
        "height": 1080,
        "url": "https://apollo.olx.in:443/v1/files/s3zc0bw7wtek-IN/image",
        "full": {
          "width": 1080,
          "height": 1671,
          "url": "https://apollo.olx.in:443/v1/files/s3zc0bw7wtek-IN/image;s=1080x1671"
        },
        "big": {
          "width": 505,
          "height": 781,
          "url": "https://apollo.olx.in:443/v1/files/s3zc0bw7wtek-IN/image;s=505x781"
        },
        "medium": {
          "width": 120,
          "height": 185,
          "url": "https://apollo.olx.in:443/v1/files/s3zc0bw7wtek-IN/image;s=120x185"
        },
        "small": {
          "width": 120,
          "height": 185,
          "url": "https://apollo.olx.in:443/v1/files/s3zc0bw7wtek-IN/image;s=120x185"
        }
      },
      {
        "id": "1949819171",
        "external_id": "a1v4aohj82442-IN",
        "width": 855,
        "height": 1080,
        "url": "https://apollo.olx.in:443/v1/files/a1v4aohj82442-IN/image",
        "full": {
          "width": 1080,
          "height": 1364,
          "url": "https://apollo.olx.in:443/v1/files/a1v4aohj82442-IN/image;s=1080x1364"
        },
        "big": {
          "width": 505,
          "height": 637,
          "url": "https://apollo.olx.in:443/v1/files/a1v4aohj82442-IN/image;s=505x637"
        },
        "medium": {
          "width": 120,
          "height": 151,
          "url": "https://apollo.olx.in:443/v1/files/a1v4aohj82442-IN/image;s=120x151"
        },
        "small": {
          "width": 120,
          "height": 151,
          "url": "https://apollo.olx.in:443/v1/files/a1v4aohj82442-IN/image;s=120x151"
        }
      },
      {
        "id": "1949819172",
        "external_id": "f9qidzdqe9k01-IN",
        "width": 824,
        "height": 1080,
        "url": "https://apollo.olx.in:443/v1/files/f9qidzdqe9k01-IN/image",
        "full": {
          "width": 1080,
          "height": 1415,
          "url": "https://apollo.olx.in:443/v1/files/f9qidzdqe9k01-IN/image;s=1080x1415"
        },
        "big": {
          "width": 505,
          "height": 661,
          "url": "https://apollo.olx.in:443/v1/files/f9qidzdqe9k01-IN/image;s=505x661"
        },
        "medium": {
          "width": 120,
          "height": 157,
          "url": "https://apollo.olx.in:443/v1/files/f9qidzdqe9k01-IN/image;s=120x157"
        },
        "small": {
          "width": 120,
          "height": 157,
          "url": "https://apollo.olx.in:443/v1/files/f9qidzdqe9k01-IN/image;s=120x157"
        }
      }
    ],
    "certified_car": false,
    "is_kyc_verified_user": false,
    "locations_resolved": {
      "COUNTRY_id": "1000001",
      "COUNTRY_name": "India",
      "ADMIN_LEVEL_1_id": "2001152",
      "ADMIN_LEVEL_1_name": "Delhi",
      "ADMIN_LEVEL_3_id": "4058659",
      "ADMIN_LEVEL_3_name": "Delhi",
      "SUBLOCALITY_LEVEL_1_id": "5327607",
      "SUBLOCALITY_LEVEL_1_name": "Babarpur"
    },
    "dealer_showroom_enabled": false,
    "artificial_boost": false,
    "display_date": "2025-10-31T14:37:05+0000",
    "isSpinViewAvailable": false,
    "user_id": "630845733",
    "created_at_first": "2025-10-31T20:06:02+05:30",
    "locations": [
      {
        "lat": 28.688,
        "lon": 77.28,
        "region_id": "2001152",
        "district_id": "5327607",
        "city_id": "4058659"
      }
    ],
    "parameters": []
  },
  {
    "id": "1825091532",
    "score": 1.0,
    "spell": {
      "id": 111,
      "key": "GEAS_ES",
      "version": "1",
      "main": true,
      "facet_disabled": false,
      "default_sorting": "DEFAULT",
      "response_type": "ARRAY"
    },
    "status": {
      "status": "active",
      "allow_edit": true,
      "display": "active",
      "translated_display": "Active",
      "flags": {
        "new": false,
        "hot": false
      },
      "allow_deactivate": true
    },
    "category_id": "93",
    "ad_id": "1825091532",
    "favorites": {
      "count": 0,
      "count_label_next": "1"
    },
    "user_tag": "olx disapproved",
    "user_name": "JeK",
    "has_phone_param": false,
    "description": "Authentic PS5 and PS4 original sealed games available at unbeatable wholesale prices! We offer genuine, brand-new, factory-sealed discs direct from authorized distributors.Why Choose Us:100% authentic and original gamesSealed packaging guaranteeWholesale rates - much cheaper than market priceDirect pickup available across Delhi NCRFast delivery serviceHow It Works:Browse and select your favorite PS5 or PS4 gamePlace your order with game preference at least 2.5 days in advanceWe arrange and prepare your stock quicklyPick up directly from our location in Delhi NCRDelivery: Personal pickup only from our Delhi NCR location. We ensure fast processing to get your games to you as soon as possible.Available For: PS5 Games  PS4 Games  Original Sealed CDs  Wholesale Bulk OrdersContact us today for stock availability and exclusive wholesale rates!",
    "created_at": "2025-10-31T20:06:02+05:30",
    "videos": [],
    "title": "Original Sealed PS5 & PS4 Games Wholesale Prices Delhi NCR Pickup Only",
    "buyer_id": "0",
    "elite_seller": false,
    "user_type": "Regular",
    "price": {
      "value": {
        "raw": 4893.0,
        "currency": {
          "iso_4217": "INR",
          "pre": "\u20b9"
        },
        "display": "\u20b9 4,893"
      },
      "key_name": "Price",
      "key": "price"
    },
    "is_business": false,
    "images": [
      {
        "id": "1949819165",
        "external_id": "7m1fkqx1vtrq-IN",
        "width": 845,
        "height": 1080,
        "url": "https://apollo.olx.in:443/v1/files/7m1fkqx1vtrq-IN/image",
        "full": {
          "width": 1080,
          "height": 1380,
          "url": "https://apollo.olx.in:443/v1/files/7m1fkqx1vtrq-IN/image;s=1080x1380"
        },
        "big": {
          "width": 505,
          "height": 645,
          "url": "https://apollo.olx.in:443/v1/files/7m1fkqx1vtrq-IN/image;s=505x645"
        },
        "medium": {
          "width": 120,
          "height": 153,
          "url": "https://apollo.olx.in:443/v1/files/7m1fkqx1vtrq-IN/image;s=120x153"
        },
        "small": {
          "width": 120,
          "height": 153,
          "url": "https://apollo.olx.in:443/v1/files/7m1fkqx1vtrq-IN/image;s=120x153"
        }
      },
      {
        "id": "1949819166",
        "external_id": "676v4v8t5t3f3-IN",
        "width": 827,
        "height": 1080,
        "url": "https://apollo.olx.in:443/v1/files/676v4v8t5t3f3-IN/image",
        "full": {
          "width": 1080,
          "height": 1410,
          "url": "https://apollo.olx.in:443/v1/files/676v4v8t5t3f3-IN/image;s=1080x1410"
        },
        "big": {
          "width": 505,
          "height": 659,
          "url": "https://apollo.olx.in:443/v1/files/676v4v8t5t3f3-IN/image;s=505x659"
        },
        "medium": {
          "width": 120,
          "height": 156,
          "url": "https://apollo.olx.in:443/v1/files/676v4v8t5t3f3-IN/image;s=120x156"
        },
        "small": {
          "width": 120,
          "height": 156,
          "url": "https://apollo.olx.in:443/v1/files/676v4v8t5t3f3-IN/image;s=120x156"
        }
      },
      {
        "id": "1949819167",
        "external_id": "aam4iqeuauj21-IN",
        "width": 835,
        "height": 1080,
        "url": "https://apollo.olx.in:443/v1/files/aam4iqeuauj21-IN/image",
        "full": {
          "width": 1080,
          "height": 1396,
          "url": "https://apollo.olx.in:443/v1/files/aam4iqeuauj21-IN/image;s=1080x1396"
        },
        "big": {
          "width": 505,
          "height": 653,
          "url": "https://apollo.olx.in:443/v1/files/aam4iqeuauj21-IN/image;s=505x653"
        },
        "medium": {
          "width": 120,
          "height": 155,
          "url": "https://apollo.olx.in:443/v1/files/aam4iqeuauj21-IN/image;s=120x155"
        },
        "small": {
          "width": 120,
          "height": 155,
          "url": "https://apollo.olx.in:443/v1/files/aam4iqeuauj21-IN/image;s=120x155"
        }
      },
      {
        "id": "1949819168",
        "external_id": "azicylofn0xg-IN",
        "width": 712,
        "height": 1080,
        "url": "https://apollo.olx.in:443/v1/files/azicylofn0xg-IN/image",
        "full": {
          "width": 1080,
          "height": 1638,
          "url": "https://apollo.olx.in:443/v1/files/azicylofn0xg-IN/image;s=1080x1638"
        },
        "big": {
          "width": 505,
          "height": 766,
          "url": "https://apollo.olx.in:443/v1/files/azicylofn0xg-IN/image;s=505x766"
        },
        "medium": {
          "width": 120,
          "height": 182,
          "url": "https://apollo.olx.in:443/v1/files/azicylofn0xg-IN/image;s=120x182"
        },
        "small": {
          "width": 120,
          "height": 182,
          "url": "https://apollo.olx.in:443/v1/files/azicylofn0xg-IN/image;s=120x182"
        }
      },
      {
        "id": "1949819169",
        "external_id": "759w826kzq8w1-IN",
        "width": 833,
        "height": 1080,
        "url": "https://apollo.olx.in:443/v1/files/759w826kzq8w1-IN/image",
        "full": {
          "width": 1080,
          "height": 1400,
          "url": "https://apollo.olx.in:443/v1/files/759w826kzq8w1-IN/image;s=1080x1400"
        },
        "big": {
          "width": 505,
          "height": 654,
          "url": "https://apollo.olx.in:443/v1/files/759w826kzq8w1-IN/image;s=505x654"
        },
        "medium": {
          "width": 120,
          "height": 155,
          "url": "https://apollo.olx.in:443/v1/files/759w826kzq8w1-IN/image;s=120x155"
        },
        "small": {
          "width": 120,
          "height": 155,
          "url": "https://apollo.olx.in:443/v1/files/759w826kzq8w1-IN/image;s=120x155"
        }
      },
      {
        "id": "1949819170",
        "external_id": "s3zc0bw7wtek-IN",
        "width": 698,
        "height": 1080,
        "url": "https://apollo.olx.in:443/v1/files/s3zc0bw7wtek-IN/image",
        "full": {
          "width": 1080,
          "height": 1671,
          "url": "https://apollo.olx.in:443/v1/files/s3zc0bw7wtek-IN/image;s=1080x1671"
        },
        "big": {
          "width": 505,
          "height": 781,
          "url": "https://apollo.olx.in:443/v1/files/s3zc0bw7wtek-IN/image;s=505x781"
        },
        "medium": {
          "width": 120,
          "height": 185,
          "url": "https://apollo.olx.in:443/v1/files/s3zc0bw7wtek-IN/image;s=120x185"
        },
        "small": {
          "width": 120,
          "height": 185,
          "url": "https://apollo.olx.in:443/v1/files/s3zc0bw7wtek-IN/image;s=120x185"
        }
      },
      {
        "id": "1949819171",
        "external_id": "a1v4aohj82442-IN",
        "width": 855,
        "height": 1080,
        "url": "https://apollo.olx.in:443/v1/files/a1v4aohj82442-IN/image",
        "full": {
          "width": 1080,
          "height": 1364,
          "url": "https://apollo.olx.in:443/v1/files/a1v4aohj82442-IN/image;s=1080x1364"
        },
        "big": {
          "width": 505,
          "height": 637,
          "url": "https://apollo.olx.in:443/v1/files/a1v4aohj82442-IN/image;s=505x637"
        },
        "medium": {
          "width": 120,
          "height": 151,
          "url": "https://apollo.olx.in:443/v1/files/a1v4aohj82442-IN/image;s=120x151"
        },
        "small": {
          "width": 120,
          "height": 151,
          "url": "https://apollo.olx.in:443/v1/files/a1v4aohj82442-IN/image;s=120x151"
        }
      },
      {
        "id": "1949819172",
        "external_id": "f9qidzdqe9k01-IN",
        "width": 824,
        "height": 1080,
        "url": "https://apollo.olx.in:443/v1/files/f9qidzdqe9k01-IN/image",
        "full": {
          "width": 1080,
          "height": 1415,
          "url": "https://apollo.olx.in:443/v1/files/f9qidzdqe9k01-IN/image;s=1080x1415"
        },
        "big": {
          "width": 505,
          "height": 661,
          "url": "https://apollo.olx.in:443/v1/files/f9qidzdqe9k01-IN/image;s=505x661"
        },
        "medium": {
          "width": 120,
          "height": 157,
          "url": "https://apollo.olx.in:443/v1/files/f9qidzdqe9k01-IN/image;s=120x157"
        },
        "small": {
          "width": 120,
          "height": 157,
          "url": "https://apollo.olx.in:443/v1/files/f9qidzdqe9k01-IN/image;s=120x157"
        }
      }
    ],
    "certified_car": false,
    "is_kyc_verified_user": false,
    "locations_resolved": {
      "COUNTRY_id": "1000001",
      "COUNTRY_name": "India",
      "ADMIN_LEVEL_1_id": "2001152",
      "ADMIN_LEVEL_1_name": "Delhi",
      "ADMIN_LEVEL_3_id": "4058659",
      "ADMIN_LEVEL_3_name": "Delhi",
      "SUBLOCALITY_LEVEL_1_id": "5327607",
      "SUBLOCALITY_LEVEL_1_name": "Babarpur"
    },
    "dealer_showroom_enabled": false,
    "artificial_boost": false,
    "display_date": "2025-10-31T14:37:05+0000",
    "isSpinViewAvailable": false,
    "user_id": "630845733",
    "created_at_first": "2025-10-31T20:06:02+05:30",
    "locations": [
      {
        "lat": 28.688,
        "lon": 77.28,
        "region_id": "2001152",
        "district_id": "5327607",
        "city_id": "4058659"
      }
    ],
    "parameters": []
  }
]